{
  "version": "5",
  "dialect": "pg",
  "entries": [
    {
      "idx": 0,
      "version": "5",
      "when": 1765044253198,
      "tag": "0000_strong_proudstar",
      "breakpoints": true
    },
    {
      "idx": 1,
      "version": "5",
      "when": 1765044663654,
      "tag": "0001_material_killer_shrike",
      "breakpoints": true
    },
    {
      "idx": 2,
      "version": "5",
      "when": 1767975604963,
      "tag": "0002_grey_the_initiative",
      "breakpoints": true
    },
    {
      "idx": 3,
      "version": "5",
      "when": 1768354392040,
      "tag": "0003_yielding_nocturne",
      "breakpoints": true
    },
    {
      "idx": 4,
      "version": "5",
      "when": 1769293239361,
      "tag": "0004_acoustic_jigsaw",
      "breakpoints": true
    }
  ]
}